LICENSE
README.md
setup.py
lavalink/__init__.py
lavalink/__main__.py
lavalink/abc.py
lavalink/client.py
lavalink/common.py
lavalink/dataio.py
lavalink/errors.py
lavalink/events.py
lavalink/filters.py
lavalink/node.py
lavalink/nodemanager.py
lavalink/player.py
lavalink/playermanager.py
lavalink/server.py
lavalink/source_decoders.py
lavalink/stats.py
lavalink/transport.py
lavalink/utfm_codec.py
lavalink/utils.py
lavalink.egg-info/PKG-INFO
lavalink.egg-info/SOURCES.txt
lavalink.egg-info/dependency_links.txt
lavalink.egg-info/entry_points.txt
lavalink.egg-info/requires.txt
lavalink.egg-info/top_level.txt